dvtDecimal/__init__.py
dvtDecimal/dvtDecimal.py
dvtDecimal/dvtDecimalTools.py
dvtDecimal-1.4.0.dist-info/METADATA
dvtDecimal-1.4.0.dist-info/WHEEL
dvtDecimal-1.4.0.dist-info/top_level.txt
dvtDecimal-1.4.0.dist-info/RECORD
