Metadata-Version: 2.1
Name: dvtDecimal
Version: 1.4.0
Summary: Repeating digits of rational numbers
Home-page: https://twitter.com/david_cobac
Author: David COBAC
Author-email: david.cobac@gmail.com
License: CC-BY-NC-SA
Keywords: rational,numbers,fraction,decimal,nombres,décimaux
Platform: UNKNOWN
Classifier: Programming Language :: Python :: 3
Classifier: Operating System :: OS Independent
